biteen_utilities/__init__.py
biteen_utilities/biteen_io.py
biteen_utilities/biteen_napari.py
biteen_utilities/biteen_pandas.py
biteen_utilities/biteen_plots.py
biteen_utilities-0.1.3.dist-info/LICENSE
biteen_utilities-0.1.3.dist-info/METADATA
biteen_utilities-0.1.3.dist-info/WHEEL
biteen_utilities-0.1.3.dist-info/top_level.txt
biteen_utilities-0.1.3.dist-info/RECORD
