Metadata-Version: 2.1
Name: biteen_utilities
Version: 0.1.3
Summary: Tools for working with single-molecule localization data.
Author: Daniel Foust
Author-email: djfoust@umich.edu
Classifier: Programming Language :: Python :: 3
Classifier: Operating System :: OS Independent
License-File: LICENSE
Requires-Dist: h5py
Requires-Dist: hdf5storage
Requires-Dist: matplotlib
Requires-Dist: matplotlib_scalebar
Requires-Dist: napari[all]
Requires-Dist: napari_animation
Requires-Dist: nd2
Requires-Dist: numpy
Requires-Dist: pandas
Requires-Dist: scikit-image
Requires-Dist: scipy
Requires-Dist: tifffile
